jcb/__init__.py
jcb/driver.py
jcb/renderer.py
jcb/observation_chronicle/conv_chronicle.py
jcb/observation_chronicle/observation_chronicle.py
jcb/observation_chronicle/satellite_chronicle.py
jcb/utilities/config_parsing.py
jcb/utilities/parse_channels.py
jcb/utilities/testing.py
jcb/utilities/trapping.py
jcb-0.1.0.dist-info/licenses/LICENSE
jcb-0.1.0.dist-info/METADATA
jcb-0.1.0.dist-info/WHEEL
jcb-0.1.0.dist-info/entry_points.txt
jcb-0.1.0.dist-info/top_level.txt
jcb-0.1.0.dist-info/RECORD
