Metadata-Version: 2.4
Name: jcb
Version: 0.1.0
Summary: JEDI Configuration Builder
Home-page: https://github.com/NOAA-EMC/jcb
Author: NOAA, NASA, JCSDA
Keywords: JEDI,JCSDA,NOAA,NASA
Requires-Python: >=3.6
License-File: LICENSE
Requires-Dist: PyYAML>=6.0
Requires-Dist: Jinja2>=3.1.2
Requires-Dist: click>=8.0
Provides-Extra: testing
Requires-Dist: pytest>=7; extra == "testing"
Requires-Dist: flake8; extra == "testing"
Requires-Dist: flake8-import-order; extra == "testing"
Dynamic: license-file
